nonebot_plugin_horserace/__init__.py
nonebot_plugin_horserace/events/Stand.json
nonebot_plugin_horserace/events/“日常，真的很日常”.json
nonebot_plugin_horserace/events/克苏鲁.json
nonebot_plugin_horserace/events/基础事件.json
nonebot_plugin_horserace/events/复刻经典事件集合v1.json
nonebot_plugin_horserace/events/崩坏集合v1.json
nonebot_plugin_horserace/events/群友日常.json
nonebot_plugin_horserace/events/芜湖事件合集.json
nonebot_plugin_horserace/events/赫尔事件集v1.json
nonebot_plugin_horserace/events/赫尔的赛马场事件簿.json
nonebot_plugin_horserace/events_main.py
nonebot_plugin_horserace/horse.py
nonebot_plugin_horserace/race_group.py
nonebot_plugin_horserace/setting.py
nonebot_plugin_horserace/start.py
nonebot_plugin_horserace-2.2.dist-info/LICENSE.txt
nonebot_plugin_horserace-2.2.dist-info/WHEEL
nonebot_plugin_horserace-2.2.dist-info/METADATA
nonebot_plugin_horserace-2.2.dist-info/RECORD
