Metadata-Version: 2.1
Name: nonebot-plugin-horserace
Version: 2.2
Summary: horserace
License: MIT
Author: shinian
Author-email: 2581846402@qq.com
Requires-Python: >=3.10,<4.0
Classifier: License :: OSI Approved :: MIT License
Classifier: Programming Language :: Python :: 3
Classifier: Programming Language :: Python :: 3.10
Requires-Dist: nonebot-adapter-onebot (>=2.1.1,<3.0.0)
Requires-Dist: nonebot-plugin-imageutils (>=0.1.6,<0.2.0)
Requires-Dist: nonebot2 (>=2.0.0-beta.4,<3.0.0)
